i3expo/__init__.py
i3expo/debounce.py
i3expo/main.py
i3expo/prtscn.so
i3expo-0.0.4.dist-info/LICENSE
i3expo-0.0.4.dist-info/METADATA
i3expo-0.0.4.dist-info/WHEEL
i3expo-0.0.4.dist-info/entry_points.txt
i3expo-0.0.4.dist-info/top_level.txt
i3expo-0.0.4.dist-info/RECORD
