Metadata-Version: 2.2
Name: i3expo
Version: 0.0.4
Summary: display current i3 workspaces
Home-page: https://github.com/laur89/i3expo
Author: Laur
License: MIT
Classifier: Programming Language :: Python :: 3
Classifier: License :: OSI Approved :: MIT License
License-File: LICENSE
Requires-Dist: pygame
Requires-Dist: pulp
Requires-Dist: i3ipc
Requires-Dist: pyxdg
Requires-Dist: Pillow
Requires-Dist: tendo
Provides-Extra: test
Requires-Dist: pytest; extra == "test"
Requires-Dist: coverage; extra == "test"
Requires-Dist: flake8; extra == "test"
Requires-Dist: black; extra == "test"
Requires-Dist: isort; extra == "test"
Requires-Dist: pytest-cov; extra == "test"
Requires-Dist: mypy; extra == "test"
Requires-Dist: gitchangelog; extra == "test"
Requires-Dist: mkdocs; extra == "test"
Dynamic: author
Dynamic: classifier
Dynamic: description
Dynamic: description-content-type
Dynamic: home-page
Dynamic: license
Dynamic: provides-extra
Dynamic: requires-dist
Dynamic: summary
